odoo/addons/stock_release_channel_shipment_advice_deliver/README.rst
odoo/addons/stock_release_channel_shipment_advice_deliver/__init__.py
odoo/addons/stock_release_channel_shipment_advice_deliver/__manifest__.py
odoo/addons/stock_release_channel_shipment_advice_deliver/data/queue_job_channel.xml
odoo/addons/stock_release_channel_shipment_advice_deliver/data/queue_job_function.xml
odoo/addons/stock_release_channel_shipment_advice_deliver/i18n/fr.po
odoo/addons/stock_release_channel_shipment_advice_deliver/i18n/it.po
odoo/addons/stock_release_channel_shipment_advice_deliver/i18n/stock_release_channel_shipment_advice_deliver.pot
odoo/addons/stock_release_channel_shipment_advice_deliver/models/__init__.py
odoo/addons/stock_release_channel_shipment_advice_deliver/models/shipment_advice.py
odoo/addons/stock_release_channel_shipment_advice_deliver/models/stock_release_channel.py
odoo/addons/stock_release_channel_shipment_advice_deliver/readme/CONTRIBUTORS
odoo/addons/stock_release_channel_shipment_advice_deliver/readme/DESCRIPTION.rst
odoo/addons/stock_release_channel_shipment_advice_deliver/readme/USAGE.rst
odoo/addons/stock_release_channel_shipment_advice_deliver/security/stock_release_channel_deliver_check_wizard.xml
odoo/addons/stock_release_channel_shipment_advice_deliver/static/description/icon.png
odoo/addons/stock_release_channel_shipment_advice_deliver/static/description/index.html
odoo/addons/stock_release_channel_shipment_advice_deliver/tests/__init__.py
odoo/addons/stock_release_channel_shipment_advice_deliver/tests/common.py
odoo/addons/stock_release_channel_shipment_advice_deliver/tests/test_stock_release_channel_deliver.py
odoo/addons/stock_release_channel_shipment_advice_deliver/tests/test_stock_release_channel_deliver_async.py
odoo/addons/stock_release_channel_shipment_advice_deliver/views/stock_release_channel.xml
odoo/addons/stock_release_channel_shipment_advice_deliver/wizards/__init__.py
odoo_addon_stock_release_channel_shipment_advice_deliver-16.0.2.0.0.1.dist-info/METADATA
odoo_addon_stock_release_channel_shipment_advice_deliver-16.0.2.0.0.1.dist-info/WHEEL
odoo_addon_stock_release_channel_shipment_advice_deliver-16.0.2.0.0.1.dist-info/top_level.txt
odoo_addon_stock_release_channel_shipment_advice_deliver-16.0.2.0.0.1.dist-info/RECORD
