Metadata-Version: 2.1
Name: odoo-addon-stock_release_channel_shipment_advice_deliver
Version: 16.0.2.0.0.1
Summary: This module adds an action to the release channel to automate the delivery of its shippings.
Home-page: https://github.com/OCA/wms
Author: ACSONE SA/NV, BCIM, Odoo Community Association (OCA)
Author-email: support@odoo-community.org
License: AGPL-3
Classifier: Programming Language :: Python
Classifier: Framework :: Odoo
Classifier: Framework :: Odoo :: 16.0
Classifier: License :: OSI Approved :: GNU Affero General Public License v3
Requires-Python: >=3.10
Requires-Dist: odoo-addon-queue-job<16.1dev,>=16.0dev
Requires-Dist: odoo-addon-stock-available-to-promise-release<16.1dev,>=16.0dev
Requires-Dist: odoo-addon-stock-release-channel<16.1dev,>=16.0dev
Requires-Dist: odoo-addon-stock-release-channel-shipment-advice<16.1dev,>=16.0dev
Requires-Dist: odoo-addon-web-notify<16.1dev,>=16.0dev
Requires-Dist: odoo<16.1dev,>=16.0a
